digital_ink_library/__init__.py
digital_ink_library/boundingbox.py
digital_ink_library/meta.py
digital_ink_library/sketch.py
digital_ink_library/stroke.py
digital_ink_library/utils.py
digital_ink_library/conversion/__init__.py
digital_ink_library/conversion/stroke3.py
digital_ink_library/serialization/__init__.py
digital_ink_library/serialization/json.py
digital_ink_library/serialization/msgpack.py
digital_ink_library-1.4.1.dist-info/LICENSE.txt
digital_ink_library-1.4.1.dist-info/METADATA
digital_ink_library-1.4.1.dist-info/WHEEL
digital_ink_library-1.4.1.dist-info/top_level.txt
digital_ink_library-1.4.1.dist-info/RECORD
