Metadata-Version: 2.1
Name: digital-ink-library
Version: 1.4.1
Summary: Library for digital ink, written in Python.
Home-page: https://github.com/DFKI-Interactive-Machine-Learning/digital-ink-library-python
Author: Alexander Prange, Michael Barz
Author-email: alexander.prange@dfki.de, michael.barz@dfki.de
License: CC BY-NC-SA 4.0
Download-URL: https://github.com/DFKI-Interactive-Machine-Learning/digital-ink-library-python/releases/download/v1.4.1/digital_ink_library-1.4.1-py3-none-any.whl
Keywords: digital pen
Platform: UNKNOWN
Requires-Python: >=3.6.0
Requires-Dist: numpy
Requires-Dist: scipy
